amauo/__init__.py
amauo/__main__.py
amauo/_version.py
amauo/cli.py
amauo/commands/HELP.md
amauo/commands/README.md
amauo/commands/__init__.py
amauo/commands/cleanup.py
amauo/commands/create.py
amauo/commands/destroy.py
amauo/commands/generate.py
amauo/commands/help.py
amauo/commands/list.py
amauo/commands/nuke.py
amauo/commands/random_ip.py
amauo/commands/readme.py
amauo/commands/setup.py
amauo/commands/validate.py
amauo/commands/version.py
amauo/core/__init__.py
amauo/core/config.py
amauo/core/constants.py
amauo/core/convention_scanner.py
amauo/core/deployment.py
amauo/core/deployment_discovery.py
amauo/core/state.py
amauo/templates/__init__.py
amauo/templates/cloud_init_templates.py
amauo/templates/library/docker.yaml
amauo/templates/library/minimal.yaml
amauo/utils/__init__.py
amauo/utils/aws.py
amauo/utils/aws_manager.py
amauo/utils/config_validator.py
amauo/utils/display.py
amauo/utils/file_uploader.py
amauo/utils/logging.py
amauo/utils/portable_cloud_init.py
amauo/utils/service_installer.py
amauo/utils/shutdown_handler.py
amauo/utils/ssh.py
amauo/utils/ssh_manager.py
amauo/utils/tables.py
amauo/utils/tarball_handler.py
amauo/utils/ui_manager.py
amauo-3.0.27.dist-info/METADATA
amauo-3.0.27.dist-info/WHEEL
amauo-3.0.27.dist-info/entry_points.txt
amauo-3.0.27.dist-info/RECORD
