Metadata-Version: 2.4
Name: amauo
Version: 3.0.27
Summary: Deploy Bacalhau compute nodes globally using AWS spot instances for cost-effective distributed computing
Project-URL: Homepage, https://tada.wang
Project-URL: Documentation, https://github.com/bacalhau-project/amauo#readme
Project-URL: Repository, https://github.com/bacalhau-project/amauo
Project-URL: Bug Tracker, https://github.com/bacalhau-project/amauo/issues
Project-URL: Project Site, https://tada.wang
Author-email: Amauo Team <hello@amauo.dev>
License-Expression: MIT
Keywords: aws,bacalhau,cloud,deployment,distributed-computing,spot-instances
Classifier: Development Status :: 4 - Beta
Classifier: Environment :: Console
Classifier: Intended Audience :: Developers
Classifier: License :: OSI Approved :: MIT License
Classifier: Operating System :: OS Independent
Classifier: Programming Language :: Python :: 3
Classifier: Programming Language :: Python :: 3.9
Classifier: Programming Language :: Python :: 3.10
Classifier: Programming Language :: Python :: 3.11
Classifier: Programming Language :: Python :: 3.12
Classifier: Topic :: Software Development :: Libraries :: Python Modules
Classifier: Topic :: System :: Distributed Computing
Classifier: Topic :: Utilities
Requires-Python: >=3.9
Requires-Dist: boto3>=1.28.0
Requires-Dist: botocore>=1.31.0
Requires-Dist: click>=8.0.0
Requires-Dist: pyyaml>=6.0
Requires-Dist: rich>=13.0.0
Requires-Dist: types-boto3[ec2]>=1.40.21
